firewall_test/__init__.py
firewall_test/__main__.py
firewall_test/ci.py
firewall_test/cli.py
firewall_test/config.py
firewall_test/shell.py
firewall_test/testdata_test.py
firewall_test/plugins/__init__.py
firewall_test/plugins/system/__init__.py
firewall_test/plugins/system/abstract.py
firewall_test/plugins/system/abstract_rule_match.py
firewall_test/plugins/system/config.py
firewall_test/plugins/system/firewall_netfilter.py
firewall_test/plugins/system/firewall_opnsense.py
firewall_test/plugins/system/system_linux_netfilter.py
firewall_test/plugins/system/system_opnsense.py
firewall_test/plugins/translate/__init__.py
firewall_test/plugins/translate/abstract.py
firewall_test/plugins/translate/linux.py
firewall_test/plugins/translate/linux_interfaces_test.py
firewall_test/plugins/translate/linux_routes_test.py
firewall_test/plugins/translate/netfilter/__init__.py
firewall_test/plugins/translate/netfilter/elements.py
firewall_test/plugins/translate/netfilter/parse.py
firewall_test/plugins/translate/netfilter/parse_test.py
firewall_test/plugins/translate/netfilter/parts.py
firewall_test/plugins/translate/netfilter/ruleset.py
firewall_test/plugins/translate/netfilter/ruleset_test.py
firewall_test/plugins/translate/opnsense/__init__.py
firewall_test/plugins/translate/opnsense/interfaces.py
firewall_test/plugins/translate/opnsense/interfaces_test.py
firewall_test/plugins/translate/opnsense/routes.py
firewall_test/plugins/translate/opnsense/routes_test.py
firewall_test/plugins/translate/opnsense/rule.py
firewall_test/plugins/translate/opnsense/ruleset.py
firewall_test/plugins/translate/opnsense/ruleset_test.py
firewall_test/simulator/01_packet_test.py
firewall_test/simulator/02_routes_test.py
firewall_test/simulator/03_firewall_init_test.py
firewall_test/simulator/04_firewall_tables_test.py
firewall_test/simulator/05_firewall_chains_test.py
firewall_test/simulator/06_firewall_e2e_test.py
firewall_test/simulator/11_loader_test.py
firewall_test/simulator/12_main_test.py
firewall_test-0.0.5.dist-info/licenses/LICENSE
firewall_test-0.0.5.dist-info/METADATA
firewall_test-0.0.5.dist-info/WHEEL
firewall_test-0.0.5.dist-info/entry_points.txt
firewall_test-0.0.5.dist-info/top_level.txt
firewall_test-0.0.5.dist-info/RECORD
