Metadata-Version: 2.4
Name: firewall-test
Version: 0.0.5
Summary: OXL Firewall Testing Framework
Author-email: Rath Pascal <contact@oxl.at>
Project-URL: Homepage, https://www.oxl.at
Project-URL: Documentation, https://github.com/O-X-L/firewall-testing-framework
Project-URL: Repository, https://github.com/O-X-L/firewall-testing-framework.git
Project-URL: Issues, https://github.com/O-X-L/firewall-testing-framework/issues
Keywords: firewall,rulesets,regression-testing,cicd,iac,infrastructure-as-code,network-security
Classifier: Programming Language :: Python :: 3
Classifier: License :: OSI Approved :: MIT License
Requires-Python: >=3.11
License-File: LICENSE
Requires-Dist: oxl-utils
Requires-Dist: requests
Dynamic: license-file
